odoo/addons/project_update_visible/README.rst
odoo/addons/project_update_visible/__init__.py
odoo/addons/project_update_visible/__manifest__.py
odoo/addons/project_update_visible/i18n/it.po
odoo/addons/project_update_visible/i18n/project_update_visible.pot
odoo/addons/project_update_visible/readme/CONTRIBUTORS.rst
odoo/addons/project_update_visible/readme/DESCRIPTION.rst
odoo/addons/project_update_visible/readme/USAGE.rst
odoo/addons/project_update_visible/static/description/icon.png
odoo/addons/project_update_visible/static/description/index.html
odoo/addons/project_update_visible/views/project_update_views.xml
odoo_addon_project_update_visible-16.0.1.0.0.2.dist-info/METADATA
odoo_addon_project_update_visible-16.0.1.0.0.2.dist-info/WHEEL
odoo_addon_project_update_visible-16.0.1.0.0.2.dist-info/top_level.txt
odoo_addon_project_update_visible-16.0.1.0.0.2.dist-info/RECORD
